stas_verber/__init__.py
stas_verber/common_functions.py
stas_verber/db_functions.py
stas_verber-0.1.dist-info/METADATA
stas_verber-0.1.dist-info/WHEEL
stas_verber-0.1.dist-info/top_level.txt
stas_verber-0.1.dist-info/RECORD
