Metadata-Version: 2.1
Name: stas-verber
Version: 0.1
Summary: This  is my first package
Home-page: UNKNOWN
Author: Stas Verber
Author-email: vrnvstanislav@yandex.ru
License: UNKNOWN
Platform: UNKNOWN
